LICENSE.md
MANIFEST.in
README.rst
pyproject.toml
requirements.core.txt
requirements.txt
setup.py
core_website_app/__init__.py
core_website_app/admin.py
core_website_app/apps.py
core_website_app/menus.py
core_website_app/settings.py
core_website_app/urls.py
core_website_app.egg-info/PKG-INFO
core_website_app.egg-info/SOURCES.txt
core_website_app.egg-info/dependency_links.txt
core_website_app.egg-info/requires.txt
core_website_app.egg-info/top_level.txt
core_website_app/commons/__init__.py
core_website_app/commons/enums.py
core_website_app/commons/exceptions.py
core_website_app/components/__init__.py
core_website_app/components/account_request/__init__.py
core_website_app/components/account_request/api.py
core_website_app/components/account_request/models.py
core_website_app/components/contact_message/__init__.py
core_website_app/components/contact_message/api.py
core_website_app/components/contact_message/models.py
core_website_app/components/help/__init__.py
core_website_app/components/help/api.py
core_website_app/components/privacy_policy/__init__.py
core_website_app/components/privacy_policy/api.py
core_website_app/components/rules_of_behavior/__init__.py
core_website_app/components/rules_of_behavior/api.py
core_website_app/components/terms_of_use/__init__.py
core_website_app/components/terms_of_use/api.py
core_website_app/migrations/0001_initial.py
core_website_app/migrations/__init__.py
core_website_app/rest/__init__.py
core_website_app/rest/urls.py
core_website_app/rest/account_request/__init__.py
core_website_app/rest/account_request/abstract_views.py
core_website_app/rest/account_request/serializers.py
core_website_app/rest/account_request/tests.py
core_website_app/rest/account_request/views.py
core_website_app/rest/contact_message/__init__.py
core_website_app/rest/contact_message/serializers.py
core_website_app/rest/contact_message/tests.py
core_website_app/rest/contact_message/views.py
core_website_app/static/core_website_app/admin/css/messages.css
core_website_app/static/core_website_app/admin/js/messages.js
core_website_app/static/core_website_app/admin/js/messages.raw.js
core_website_app/static/core_website_app/admin/js/user_requests.js
